django_hawk/__init__.py
django_hawk/authentication.py
django_hawk/middleware.py
django_hawk/py.typed
django_hawk/settings.py
django_hawk/tests/__init__.py
django_hawk/tests/settings.py
django_hawk/tests/test_views.py
django_hawk/tests/test_views_django.py
django_hawk/tests/urls.py
django_hawk/tests/views.py
django_hawk/utils.py
django_hawk-1.2.4.dist-info/LICENSE
django_hawk-1.2.4.dist-info/METADATA
django_hawk-1.2.4.dist-info/WHEEL
django_hawk-1.2.4.dist-info/RECORD
