Metadata-Version: 2.1
Name: django-hawk
Version: 1.2.4
Summary: Authenticate Django Views with HAWK
Home-page: https://github.com/uktrade/django-hawk
License: MIT
Keywords: django
Author: Cameron Lamb
Author-email: live.services@digital.trade.gov.uk
Requires-Python: >=3.8,<4.0
Classifier: License :: OSI Approved :: MIT License
Classifier: Programming Language :: Python :: 3
Classifier: Programming Language :: Python :: 3.8
Classifier: Programming Language :: Python :: 3.9
Classifier: Programming Language :: Python :: 3.10
Classifier: Programming Language :: Python :: 3.11
Classifier: Programming Language :: Python :: 3.12
Requires-Dist: Django (>=4.2,<6)
Requires-Dist: mohawk (>=1.0.0,<2.0)
